gecnk/__init__.py
gecnk/datasets.py
gecnk/json_reader.py
gecnk/noise.py
gecnk/noise_generate.py
gecnk/tokenizer.py
gecnk/resources/__init__.py
gecnk/resources/config.py
gec_noise_generator_ko-0.1.2.dist-info/LICENSE
gec_noise_generator_ko-0.1.2.dist-info/METADATA
gec_noise_generator_ko-0.1.2.dist-info/WHEEL
gec_noise_generator_ko-0.1.2.dist-info/top_level.txt
gec_noise_generator_ko-0.1.2.dist-info/RECORD
