Metadata-Version: 2.1
Name: gec_noise_generator_ko
Version: 0.1.2
Summary: Noise Generator for Korean Text
Home-page: https://github.com/JKJIN1999/gec_noise_generator_ko
Author: Jugyeong Kim
Author-email: jugyeongkim911@gmail.com
License: UNKNOWN
Project-URL: Bug Tracker, https://github.com/JKJIN1999/gec_noise_generator_ko/issues
Platform: UNKNOWN
Classifier: Programming Language :: Python :: 3
Classifier: License :: OSI Approved :: MIT License
Classifier: Operating System :: OS Independent
Requires-Python: >=3.7
License-File: LICENSE
